README.rst
setup.cfg
setup.py
pyramid_appengine/__init__.py
pyramid_appengine.egg-info/PKG-INFO
pyramid_appengine.egg-info/SOURCES.txt
pyramid_appengine.egg-info/dependency_links.txt
pyramid_appengine.egg-info/entry_points.txt
pyramid_appengine.egg-info/not-zip-safe
pyramid_appengine.egg-info/requires.txt
pyramid_appengine.egg-info/top_level.txt
pyramid_appengine/scaffolds/__init__.py