Metadata-Version: 1.1
Name: pyramid-appengine
Version: 0.8.4
Summary: Scaffold + Tools for creating/developing pyramid applications on Google App Engine
Home-page: https://github.com/twillis/pyramid_appengine
Author: Tom Willis
Author-email: me@twillis.me
License: UNKNOWN
Keywords: web pyramid pylons google-app-engine
Platform: UNKNOWN
Classifier: Intended Audience :: Developers
Classifier: Programming Language :: Python
Classifier: Programming Language :: Python :: 2.7
Classifier: Programming Language :: Python :: Implementation :: CPython
Classifier: Framework :: Pyramid
Classifier: Topic :: Internet :: WWW/HTTP
Classifier: Topic :: Internet :: WWW/HTTP :: WSGI
